zpodsdk/__init__.py
zpodsdk/api/__init__.py
zpodsdk/api/components/__init__.py
zpodsdk/api/components/components_disable.py
zpodsdk/api/components/components_enable.py
zpodsdk/api/components/components_get.py
zpodsdk/api/components/components_get_all.py
zpodsdk/api/components/components_upload.py
zpodsdk/api/components/components_upload_filesize.py
zpodsdk/api/endpoints/__init__.py
zpodsdk/api/endpoints/endpoints_create.py
zpodsdk/api/endpoints/endpoints_delete.py
zpodsdk/api/endpoints/endpoints_enet_create.py
zpodsdk/api/endpoints/endpoints_enet_delete.py
zpodsdk/api/endpoints/endpoints_enet_get.py
zpodsdk/api/endpoints/endpoints_enet_get_all.py
zpodsdk/api/endpoints/endpoints_get.py
zpodsdk/api/endpoints/endpoints_get_all.py
zpodsdk/api/endpoints/endpoints_permissions_get_all.py
zpodsdk/api/endpoints/endpoints_permissions_groups_add.py
zpodsdk/api/endpoints/endpoints_permissions_groups_remove.py
zpodsdk/api/endpoints/endpoints_permissions_users_add.py
zpodsdk/api/endpoints/endpoints_permissions_users_remove.py
zpodsdk/api/endpoints/endpoints_update.py
zpodsdk/api/endpoints/endpoints_verify.py
zpodsdk/api/libraries/__init__.py
zpodsdk/api/libraries/libraries_create.py
zpodsdk/api/libraries/libraries_delete.py
zpodsdk/api/libraries/libraries_get.py
zpodsdk/api/libraries/libraries_get_all.py
zpodsdk/api/libraries/libraries_resync.py
zpodsdk/api/libraries/libraries_update.py
zpodsdk/api/permission_groups/__init__.py
zpodsdk/api/permission_groups/permission_groups_create.py
zpodsdk/api/permission_groups/permission_groups_delete.py
zpodsdk/api/permission_groups/permission_groups_get.py
zpodsdk/api/permission_groups/permission_groups_get_all.py
zpodsdk/api/permission_groups/permission_groups_update.py
zpodsdk/api/permission_groups/permission_groups_users_add.py
zpodsdk/api/permission_groups/permission_groups_users_delete.py
zpodsdk/api/permission_groups/permission_groups_users_get_all.py
zpodsdk/api/profiles/__init__.py
zpodsdk/api/profiles/profiles_create.py
zpodsdk-0.7.2.dist-info/METADATA
zpodsdk-0.7.2.dist-info/WHEEL
zpodsdk-0.7.2.dist-info/RECORD
