Metadata-Version: 2.1
Name: zpodsdk
Version: 0.7.2
Summary: A client library for accessing zPod API
Requires-Python: >=3.8.1,<4.0.0
Classifier: Programming Language :: Python :: 3
Classifier: Programming Language :: Python :: 3.9
Classifier: Programming Language :: Python :: 3.10
Classifier: Programming Language :: Python :: 3.11
Classifier: Programming Language :: Python :: 3.12
Requires-Dist: attrs (==23.2.0)
Requires-Dist: httpx (==0.27.0)
Requires-Dist: python-dateutil (==2.9.0.post0)
